duckdb_kernel/__init__.py
duckdb_kernel/__main__.py
duckdb_kernel/kernel.py
duckdb_kernel/kernel_template.json
duckdb_kernel/duckdb/kernel.json
duckdb_kernel/duckdb_connect/kernel.json
duckdb_kernel-0.5.0.data/data/share/jupyter/kernels/duckdb/kernel.json
duckdb_kernel-0.5.0.data/data/share/jupyter/kernels/duckdb_connect/kernel.json
duckdb_kernel-0.5.0.dist-info/LICENSE.txt
duckdb_kernel-0.5.0.dist-info/METADATA
duckdb_kernel-0.5.0.dist-info/WHEEL
duckdb_kernel-0.5.0.dist-info/top_level.txt
duckdb_kernel-0.5.0.dist-info/RECORD
