Metadata-Version: 2.1
Name: duckdb-kernel
Version: 0.5.0
Summary: UNKNOWN
Home-page: https://github.com/suyin1203/duckdb_kernel
Author: suyin
License: MIT
Platform: UNKNOWN
Classifier: Framework :: IPython
Classifier: License :: OSI Approved :: MIT License
Classifier: Programming Language :: Python :: 3.4
Classifier: Programming Language :: Python :: 3.5
Classifier: Programming Language :: Python :: 3.6
Classifier: Programming Language :: Python :: 3.7
Classifier: Programming Language :: Python :: 3.8
Classifier: Programming Language :: Python :: 3.9
Classifier: Programming Language :: Python :: 3.10
Classifier: Programming Language :: Python :: 3.11
Classifier: Topic :: System :: Shells
Requires: duckdb
Requires: tabulate
Requires: ipython
Requires-Dist: duckdb
Requires-Dist: tabulate
Requires-Dist: ipython
